LICENSE.rst
MANIFEST.in
README.rst
RELNOTES.rst
setup.cfg
setup.py
fuzzinator/PKGDATA.json
fuzzinator/__init__.py
fuzzinator/__main__.py
fuzzinator/call_job.py
fuzzinator/config.py
fuzzinator/controller.py
fuzzinator/email_listener.py
fuzzinator/executor.py
fuzzinator/fuzz_job.py
fuzzinator/listener.py
fuzzinator/mongo_driver.py
fuzzinator/pkgdata.py
fuzzinator/reduce_job.py
fuzzinator/update_job.py
fuzzinator/validate_job.py
fuzzinator.egg-info/PKG-INFO
fuzzinator.egg-info/SOURCES.txt
fuzzinator.egg-info/dependency_links.txt
fuzzinator.egg-info/entry_points.txt
fuzzinator.egg-info/not-zip-safe
fuzzinator.egg-info/requires.txt
fuzzinator.egg-info/top_level.txt
fuzzinator/call/__init__.py
fuzzinator/call/anonymize_decorator.py
fuzzinator/call/callable_decorator.py
fuzzinator/call/exit_code_filter.py
fuzzinator/call/file_reader_decorator.py
fuzzinator/call/file_writer_decorator.py
fuzzinator/call/gdb_backtrace_decorator.py
fuzzinator/call/lldb_backtrace_decorator.py
fuzzinator/call/platform_info_decorator.py
fuzzinator/call/regex_filter.py
fuzzinator/call/stdin_subprocess_call.py
fuzzinator/call/stream_monitored_subprocess_call.py
fuzzinator/call/subprocess_call.py
fuzzinator/call/subprocess_property_decorator.py
fuzzinator/call/test_runner_subprocess_call.py
fuzzinator/call/unique_id_decorator.py
fuzzinator/fuzzer/__init__.py
fuzzinator/fuzzer/afl_runner.py
fuzzinator/fuzzer/byte_flip_decorator.py
fuzzinator/fuzzer/file_writer_decorator.py
fuzzinator/fuzzer/list_directory.py
fuzzinator/fuzzer/random_content.py
fuzzinator/fuzzer/subprocess_runner.py
fuzzinator/fuzzer/tornado_decorator.py
fuzzinator/reduce/__init__.py
fuzzinator/reduce/picire.py
fuzzinator/reduce/picire_tester.py
fuzzinator/reduce/picireny.py
fuzzinator/tracker/__init__.py
fuzzinator/tracker/base.py
fuzzinator/tracker/bugzilla.py
fuzzinator/tracker/github.py
fuzzinator/tracker/monorail.py
fuzzinator/ui/__init__.py
fuzzinator/ui/arg_parser.py
fuzzinator/ui/cli/__init__.py
fuzzinator/ui/cli/__main__.py
fuzzinator/ui/cli/cli.py
fuzzinator/ui/cli/cli_listener.py
fuzzinator/ui/tui/__init__.py
fuzzinator/ui/tui/__main__.py
fuzzinator/ui/tui/button.py
fuzzinator/ui/tui/decor_widgets.py
fuzzinator/ui/tui/dialogs.py
