Metadata-Version: 1.0
Name: fuzzinator
Version: 18.3.1
Summary: Fuzzinator Random Testing Framework
Home-page: https://github.com/renatahodovan/fuzzinator
Author: Renata Hodovan, Akos Kiss
Author-email: hodovan@inf.u-szeged.hu, akiss@inf.u-szeged.hu
License: BSD
Platform: UNKNOWN
